configs/__init__.py
configs/asgi.py
configs/settings.py
configs/urls.py
configs/wsgi.py
examples/__init__.py
examples/apps.py
examples/models.py
examples/serializers.py
examples/signals.py
sha_accounts/__init__.py
sha_accounts/apps.py
sha_accounts/permissions.py
sha_accounts/urls.py
sha_accounts/backends/__init__.py
sha_accounts/backends/authentications.py
sha_accounts/managers/__init__.py
sha_accounts/managers/user_manager.py
sha_accounts/migrations/0001_initial.py
sha_accounts/migrations/__init__.py
sha_accounts/models/__init__.py
sha_accounts/models/permission_models.py
sha_accounts/models/user_models.py
sha_accounts/serializers/__init__.py
sha_accounts/serializers/base.py
sha_accounts/serializers/profile_serializers.py
sha_accounts/serializers/user_serializers.py
sha_accounts/signals/__init__.py
sha_accounts/signals/receivers.py
sha_accounts/signals/signals.py
sha_accounts/tests/__init__.py
sha_accounts/tests/base_test.py
sha_accounts/tests/test_models.py
sha_accounts/tests/test_serializers.py
sha_accounts/tests/test_utils.py
sha_accounts/tests/test_views.py
sha_accounts/utils/__init__.py
sha_accounts/utils/import_util.py
sha_accounts/utils/jwt.py
sha_accounts/views/__init__.py
sha_accounts/views/user_views.py
sha_accounts-0.2.0.dist-info/LICENSE
sha_accounts-0.2.0.dist-info/METADATA
sha_accounts-0.2.0.dist-info/WHEEL
sha_accounts-0.2.0.dist-info/top_level.txt
sha_accounts-0.2.0.dist-info/RECORD
